addresser/__init__.py
addresser/config.py
addresser/parser.py
addresser/patterns.py
addresser/utils.py
addresser-1.2.0.dist-info/LICENSE
addresser-1.2.0.dist-info/METADATA
addresser-1.2.0.dist-info/WHEEL
addresser-1.2.0.dist-info/top_level.txt
addresser-1.2.0.dist-info/RECORD
