Metadata-Version: 2.1
Name: addresser
Version: 1.2.0
Summary: A Python port of the `parse-address` npm library
Home-page: https://github.com/consbio/addresser
License: MIT
Keywords: address parser normalizer usa us parse-address
Platform: UNKNOWN
Classifier: Programming Language :: Python
Classifier: Programming Language :: Python :: 3
Classifier: Programming Language :: Python :: 3.7
Classifier: Programming Language :: Python :: 3.8
Requires-Python: >=3.4
